task_5/__init__.py
task_5/__main__.py
task_5_something_something-0.1.0.dist-info/METADATA
task_5_something_something-0.1.0.dist-info/WHEEL
task_5_something_something-0.1.0.dist-info/top_level.txt
task_5_something_something-0.1.0.dist-info/RECORD
