Metadata-Version: 2.1
Name: task_5_something_something
Version: 0.1.0
Summary: Описание моего Python-пакета
Author-email: Central University Person 1 <d.gordeev@edu.centraluniversity.ru>
License: MIT
Requires-Python: >=3.12
